{"sold_price":"606,100","address":"1105 - 3300 Don Mills Road","bedNum":"2","bathNum":"2","sqarefootage":"1200-1399","soldOn":"Aug 10, 2020","Type":"Condo","Style":"Apartment","Size":"1200-1399 sqft","Lot Size":null,"Age":"No Data","Taxes":"$1,577 /yr","Walk Score":null,"Days on Site":"6 (Aug 4, 2020)","Pets":"Restrict","Maintenance Fees":"$900 /mo","Lease Term":null,"Possession":null,"All Inclusive":null,"Amenities":{"Groceries":["8 km","2 km","4 km"],"Liquor Store":["6 km","4 km","6 km"],"Restaurants":["8 km","8 km","8 km"],"Coffee":["8 km","8 km","2 km"],"Bank":["2 km","3 km","3 km"],"Gas Station":["8 km","6 km","1 km"],"Health & Fitness":["1 km","1 km","1 km"],"Park":["1 km","5 km","6 km"],"Library":["5 km","6 km","6 km"],"Medical Care":["1 km","5 km","7 km"],"Pharmacy":["3 km","2 km","9 km"],"Mall":["1 km","8 km","8 km"],"Movie Theatre":["7 km","1 km","1 km"]},"Nearest Schools":[{"type":"Elementary","distance":"0.41 km","rating":"9.9"},{"type":"Elementary","distance":"0.83 km","rating":"n/a"},{"type":"Elementary","distance":"0.92 km","rating":"10"},{"type":"Secondary","distance":"3.31 km","rating":"3.8"},{"type":"Secondary","distance":"2.59 km","rating":"7"},{"type":"Secondary","distance":"10.77 km","rating":"9.2"}],"pageNum":105,"weblink":"https://www.zolo.ca/toronto-real-estate/3300-don-mills-road/1105"}