{"sold_price":"1,500,000","address":"12 Beveridge Drive","bedNum":"5","bathNum":"4","sqarefootage":"n/a","soldOn":"Aug 07, 2020","Type":"Detached","Style":"2-Storey","Size":"No Data","Lot Size":"60.00 x 106.00 Feet","Age":"No Data","Taxes":"$5,637 /yr","Walk Score":null,"Days on Site":"21 (Jul 17, 2020)","Pets":null,"Maintenance Fees":null,"Lease Term":null,"Possession":null,"All Inclusive":null,"Amenities":{"Groceries":["3 km","4 km","9 km"],"Liquor Store":["3 km","3 km","6 km"],"Restaurants":["8 km","3 km","9 km"],"Coffee":["6 km","7 km","4 km"],"Bank":["4 km","2 km","2 km"],"Gas Station":["8 km","5 km","2 km"],"Health & Fitness":["3 km","4 km","8 km"],"Park":["7 km","9 km","5 km"],"Library":["6 km","6 km","4 km"],"Medical Care":["4 km","5 km","3 km"],"Pharmacy":["4 km","9 km","5 km"],"Mall":["2 km","2 km","3 km"],"Movie Theatre":["3 km","5 km","1 km"]},"Nearest Schools":[{"type":"Elementary","distance":"0.62 km","rating":"6.8"},{"type":"Elementary","distance":"0.97 km","rating":"5.9"},{"type":"Elementary","distance":"6.04 km","rating":"10"},{"type":"Secondary","distance":"0.67 km","rating":"6.4"},{"type":"Secondary","distance":"1.46 km","rating":"6"},{"type":"Secondary","distance":"7.04 km","rating":"8.9"}],"pageNum":117,"weblink":"https://www.zolo.ca/toronto-real-estate/12-beveridge-drive"}