{"sold_price":"985,000","address":"24 Guillet Street","bedNum":"3+1","bathNum":"4","sqarefootage":"2000-2500","soldOn":"Sep 02, 2020","Type":"Att/Row/Twnhouse","Style":"3-Storey","Size":"2000-2500 sqft","Lot Size":"17.56 x 90.98 Feet","Age":"No Data","Taxes":"$3,658 /yr","Walk Score":null,"Days on Site":"7 (Aug 26, 2020)","Pets":null,"Maintenance Fees":null,"Lease Term":null,"Possession":null,"All Inclusive":null,"Amenities":{"Groceries":["9 km","4 km","3 km"],"Liquor Store":["2 km","9 km","8 km"],"Restaurants":["7 km","8 km","1 km"],"Coffee":["7 km","9 km","9 km"],"Bank":["9 km","6 km","4 km"],"Gas Station":["8 km","3 km","1 km"],"Health & Fitness":["6 km","1 km","5 km"],"Park":["4 km","5 km","6 km"],"Library":["7 km","2 km","2 km"],"Medical Care":["3 km","1 km","7 km"],"Pharmacy":["3 km","1 km","6 km"],"Mall":["4 km","4 km","1 km"],"Movie Theatre":["3 km","3 km","3 km"]},"Nearest Schools":[{"type":"Elementary","distance":"0.77 km","rating":"5.8"},{"type":"Elementary","distance":"1.22 km","rating":"6.4"},{"type":"Elementary","distance":"9.96 km","rating":"10"},{"type":"Secondary","distance":"1.48 km","rating":"7.6"},{"type":"Secondary","distance":"2.85 km","rating":"4"},{"type":"Secondary","distance":"9.94 km","rating":"8.9"}],"pageNum":1,"weblink":"https://www.zolo.ca/toronto-real-estate/24-guillet-street"}