{"sold_price":"1,448,000","address":"701W - 500 Queens Quay W","bedNum":"2","bathNum":"2","sqarefootage":"1200-1399","soldOn":"Jul 27, 2020","Type":"Condo","Style":"Apartment","Size":"1200-1399 sqft","Lot Size":null,"Age":"No Data","Taxes":"$3,832 /yr","Walk Score":null,"Days on Site":"18 (Jul 9, 2020)","Pets":"Restrict","Maintenance Fees":"$972 /mo","Lease Term":null,"Possession":null,"All Inclusive":null,"Amenities":{"Groceries":["3 km","7 km","9 km"],"Liquor Store":["5 km","8 km","9 km"],"Restaurants":["6 km","2 km","9 km"],"Coffee":["3 km","9 km","6 km"],"Bank":["9 km","8 km","9 km"],"Gas Station":["4 km","5 km","6 km"],"Health & Fitness":["5 km","3 km","2 km"],"Park":["8 km","2 km","4 km"],"Library":["7 km","9 km","4 km"],"Medical Care":["4 km","1 km","6 km"],"Pharmacy":["8 km","7 km","6 km"],"Mall":["8 km","6 km","9 km"],"Movie Theatre":["3 km","4 km","4 km"]},"Nearest Schools":[{"type":"Elementary","distance":"1.03 km","rating":"n/a"},{"type":"Elementary","distance":"1.39 km","rating":"3.9"},{"type":"Elementary","distance":"2.36 km","rating":"9.9"},{"type":"Secondary","distance":"2.97 km","rating":"7.6"},{"type":"Secondary","distance":"2.99 km","rating":"3.1"},{"type":"Secondary","distance":"8.08 km","rating":"8.8"}],"pageNum":170,"weblink":"https://www.zolo.ca/toronto-real-estate/500-queen-quay-west/701w"}